ez2bruteforce/__init__.py
ez2bruteforce/__init__.pyi
ez2bruteforce/problem.py
ez2bruteforce/problem.pyi
ez2bruteforce/solver.py
ez2bruteforce/solver.pyi
ez2bruteforce/utils.py
ez2bruteforce/utils.pyi
ez2bruteforce-0.0.2.dist-info/LICENSE
ez2bruteforce-0.0.2.dist-info/METADATA
ez2bruteforce-0.0.2.dist-info/WHEEL
ez2bruteforce-0.0.2.dist-info/top_level.txt
ez2bruteforce-0.0.2.dist-info/RECORD
