Metadata-Version: 2.1
Name: ez2bruteforce
Version: 0.0.2
Summary: package to solve POW(proof of work) with no pain
Home-page: https://github.com/pypa/sampleproject
Author: syheliel
Author-email: syheliel@protonmail.com
License: UNKNOWN
Project-URL: Bug Tracker, https://github.com/syheliel/ez2bruteforce/issues
Platform: UNKNOWN
Classifier: Programming Language :: Python :: 3
Classifier: License :: OSI Approved :: Apache Software License
Classifier: Operating System :: OS Independent
Requires-Python: >=3.6
License-File: LICENSE
